lazyscribe_onnx/__init__.py
lazyscribe_onnx/_meta.py
lazyscribe_onnx-0.1.1.dist-info/licenses/LICENSE
lazyscribe_onnx-0.1.1.dist-info/METADATA
lazyscribe_onnx-0.1.1.dist-info/WHEEL
lazyscribe_onnx-0.1.1.dist-info/entry_points.txt
lazyscribe_onnx-0.1.1.dist-info/top_level.txt
lazyscribe_onnx-0.1.1.dist-info/RECORD
