Metadata-Version: 2.4
Name: lazyscribe-onnx
Version: 0.1.1
Summary: ONNX model artifact handling for lazyscribe
Author-email: Akshay Gupta <akgcodes@gmail.com>
License: MIT license
Project-URL: Documentation, https://github.com/lazyscribe/lazyscribe-onnx
Project-URL: Repository, https://github.com/lazyscribe/lazyscribe-onnx
Classifier: Development Status :: 3 - Alpha
Classifier: License :: OSI Approved :: MIT License
Classifier: Natural Language :: English
Classifier: Programming Language :: Python :: 3
Classifier: Programming Language :: Python :: 3 :: Only
Classifier: Programming Language :: Python :: 3.10
Classifier: Programming Language :: Python :: 3.11
Classifier: Programming Language :: Python :: 3.12
Classifier: Programming Language :: Python :: 3.13
Requires-Python: >=3.10.0
License-File: LICENSE
Requires-Dist: attrs<=25.4.0,>=21.2.0
Requires-Dist: lazyscribe<3,>=2.0.0
Requires-Dist: onnx<=1.20.0,>=1.12.0
Requires-Dist: python-slugify<=8.0.4,>=5.0.0
Provides-Extra: build
Requires-Dist: build; extra == "build"
Requires-Dist: commitizen; extra == "build"
Requires-Dist: twine; extra == "build"
Requires-Dist: wheel; extra == "build"
Provides-Extra: qa
Requires-Dist: edgetest; extra == "qa"
Requires-Dist: mypy; extra == "qa"
Requires-Dist: pre-commit; extra == "qa"
Requires-Dist: ruff; extra == "qa"
Requires-Dist: types-python-slugify; extra == "qa"
Requires-Dist: uv; extra == "qa"
Provides-Extra: tests
Requires-Dist: pytest; extra == "tests"
Requires-Dist: pytest-cov; extra == "tests"
Requires-Dist: time-machine; extra == "tests"
Provides-Extra: dev
Requires-Dist: lazyscribe-onnx[build]; extra == "dev"
Requires-Dist: lazyscribe-onnx[qa]; extra == "dev"
Requires-Dist: lazyscribe-onnx[tests]; extra == "dev"
Dynamic: license-file
